__init__.py
maclookup/__init__.py
maclookup/api_client.py
maclookup/requester.py
maclookup/exceptions/__init__.py
maclookup/exceptions/access_denied_exception.py
maclookup/exceptions/authorization_required_exception.py
maclookup/exceptions/empty_response_exception.py
maclookup/exceptions/invalid_mac_or_oui_exception.py
maclookup/exceptions/not_enough_credits_exception.py
maclookup/exceptions/server_error_exception.py
maclookup/exceptions/unknown_output_format_exception.py
maclookup/exceptions/unparsable_response_exception.py
maclookup/models/__init__.py
maclookup/models/block_details.py
maclookup/models/mac_address_details.py
maclookup/models/response_model.py
maclookup/models/vendor_details.py
maclookup-1.0.3.dist-info/METADATA
maclookup-1.0.3.dist-info/RECORD
maclookup-1.0.3.dist-info/WHEEL
maclookup-1.0.3.dist-info/top_level.txt
