Metadata-Version: 2.1
Name: maclookup
Version: 1.0.3
Summary: Python client library for macaddress.io API.
Home-page: https://github.com/CodeLineFi/maclookup-python
Author: CodeLine OY
Author-email: support@macaddress.io
License: MIT
Keywords: mac,oui,mac lookup,oui lookup,mac address lookup,macaddress.io,mac api,oui api
Platform: UNKNOWN
Classifier: Development Status :: 5 - Production/Stable
Classifier: Intended Audience :: Developers
Classifier: License :: OSI Approved :: MIT License
Classifier: Operating System :: Unix
Classifier: Operating System :: POSIX
Classifier: Operating System :: Microsoft :: Windows
Classifier: Programming Language :: Python
Classifier: Programming Language :: Python :: 2.7
Classifier: Programming Language :: Python :: 3
Classifier: Programming Language :: Python :: 3.6
Classifier: Programming Language :: Python :: Implementation :: CPython
Classifier: Topic :: Utilities
Provides-Extra: dev
